setup.py
GPS_Tools/GPS_danger_zone_calc.py
GPS_Tools/GPS_extract_corners.py
GPS_Tools/GPS_module.py
GPS_Tools/__init__.py
GPS_Tools/data_fitter_tools.py
GPS_Tools/functools.py
GPS_Tools/loc_calculations.py
GPS_Tools/loc_utils.py
gps_tools_package.egg-info/PKG-INFO
gps_tools_package.egg-info/SOURCES.txt
gps_tools_package.egg-info/dependency_links.txt
gps_tools_package.egg-info/requires.txt
gps_tools_package.egg-info/top_level.txt